testjson/__init__.py
testjson/types.py
testjson/validator.py
testjson-0.1a1.dist-info/entry_points.txt
testjson-0.1a1.dist-info/LICENSE
testjson-0.1a1.dist-info/WHEEL
testjson-0.1a1.dist-info/METADATA
testjson-0.1a1.dist-info/RECORD
