Metadata-Version: 2.1
Name: testjson
Version: 0.1a1
Summary: jsontest JSON validation helper
Author-email: Mark Canterbury <markc@tencastle.com>
Requires-Python: >=3.7
Classifier: License :: OSI Approved :: MIT License
Requires-Dist: jsonschema >= 4
Requires-Dist: pytest ; extra == "test"
Requires-Dist: tests ; extra == "testpaths"
Provides-Extra: test
Provides-Extra: testpaths
